LinkedListMazeSolver/__init__.py
LinkedListMazeSolver/maze_solver.py
LinkedListMazeSolver-1.0.0.dist-info/LICENSE.txt
LinkedListMazeSolver-1.0.0.dist-info/METADATA
LinkedListMazeSolver-1.0.0.dist-info/WHEEL
LinkedListMazeSolver-1.0.0.dist-info/top_level.txt
LinkedListMazeSolver-1.0.0.dist-info/RECORD
