Metadata-Version: 2.1
Name: LinkedListMazeSolver
Version: 1.0.0
Summary: This class is designed to solve a linked-list dictonary maze using the A* or Breadth-First algorithms. It takes a maze as input, represented as a dictionary where each key represents a room and the exits value is another dictionary that contains the exits of the room. 
Home-page: https://github.com/badhex/LinkedListMazeSolver
Author: badhex
Author-email: badhex@inflict.io
License: MIT
License-File: LICENSE.txt
